parafields/__init__.py
parafields/_parafields.cp312-win_amd64.pyd
parafields/_parafields.cpp
parafields/exceptions.py
parafields/field.py
parafields/interactive.py
parafields/mpi.py
parafields/stochastic.json
parafields/trend.json
parafields/utils.py
parafields-1.0.2.data/data/CMakeLists.txt
parafields-1.0.2.data/data/LICENSE.md
parafields-1.0.2.data/data/pyproject.toml
parafields-1.0.2.data/data/setup.py
parafields-1.0.2.data/data/cmake/FindFFTW.cmake
parafields-1.0.2.data/data/cmake/external.cmake.in
parafields-1.0.2.data/data/cmake/fftw3-toplevel.cmake
parafields-1.0.2.data/data/include/parafields/python/loadbalance.hh
parafields-1.0.2.data/data/include/parafields/python/mpi.hh
parafields-1.0.2.data/data/include/parafields/python/traits.hh
parafields-1.0.2.data/data/src/parafields.egg-info/PKG-INFO
parafields-1.0.2.data/data/src/parafields.egg-info/SOURCES.txt
parafields-1.0.2.data/data/src/parafields.egg-info/dependency_links.txt
parafields-1.0.2.data/data/src/parafields.egg-info/not-zip-safe
parafields-1.0.2.data/data/src/parafields.egg-info/requires.txt
parafields-1.0.2.data/data/src/parafields.egg-info/top_level.txt
parafields-1.0.2.dist-info/LICENSE.md
parafields-1.0.2.dist-info/METADATA
parafields-1.0.2.dist-info/WHEEL
parafields-1.0.2.dist-info/top_level.txt
parafields-1.0.2.dist-info/RECORD
