Metadata-Version: 2.1
Name: parafields
Version: 1.0.2
Summary: Parallel Parameter Fields for Uncertainty Quantification
Maintainer-email: Dominic Kempf <dominic.kempf@iwr.uni-heidelberg.de>
License: BSD-3
Classifier: Programming Language :: Python :: 3
Classifier: Operating System :: OS Independent
Classifier: License :: OSI Approved :: BSD License
Requires-Python: >=3.8
License-File: LICENSE.md
Requires-Dist: jsonschema<4
Requires-Dist: matplotlib
Requires-Dist: mpi4py
Requires-Dist: numpy
Requires-Dist: Pillow
Provides-Extra: docs
Requires-Dist: docutils<0.17; extra == "docs"
Requires-Dist: ipykernel; extra == "docs"
Requires-Dist: nbsphinx; extra == "docs"
Requires-Dist: nbsphinx-link; extra == "docs"
Requires-Dist: sphinx; extra == "docs"
Requires-Dist: sphinx_mdinclude; extra == "docs"
Requires-Dist: sphinx_rtd_theme; extra == "docs"
Provides-Extra: jupyter
Requires-Dist: IPython; extra == "jupyter"
Requires-Dist: ipywidgets; extra == "jupyter"
Requires-Dist: ipywidgets-jsonschema; extra == "jupyter"
Requires-Dist: wrapt; extra == "jupyter"
Provides-Extra: tests
Requires-Dist: lcov_cobertura; extra == "tests"
Requires-Dist: nbval; extra == "tests"
Requires-Dist: pytest; extra == "tests"
Requires-Dist: pytest-cov; extra == "tests"
Requires-Dist: pytest-mpi; extra == "tests"
